aw_jupyter
